build/lib/build/lib/build/lib/build/lib/build/lib/build/lib/build/lib/clicksign/__init__.py
build/lib/build/lib/build/lib/build/lib/build/lib/build/lib/build/lib/clicksign/application/create_document.py
build/lib/build/lib/build/lib/build/lib/build/lib/build/lib/build/lib/clicksign/application/create_envelope.py
build/lib/build/lib/build/lib/build/lib/build/lib/build/lib/build/lib/clicksign/application/create_required_auth.py
build/lib/build/lib/build/lib/build/lib/build/lib/build/lib/build/lib/clicksign/application/create_signer.py
build/lib/build/lib/build/lib/build/lib/build/lib/build/lib/build/lib/clicksign/application/update_envelope.py
build/lib/build/lib/build/lib/build/lib/build/lib/build/lib/build/lib/clicksign/domain/document.py
build/lib/build/lib/build/lib/build/lib/build/lib/build/lib/build/lib/clicksign/domain/envelope.py
build/lib/build/lib/build/lib/build/lib/build/lib/build/lib/build/lib/clicksign/domain/required_auth.py
build/lib/build/lib/build/lib/build/lib/build/lib/build/lib/build/lib/clicksign/domain/send_email.py
build/lib/build/lib/build/lib/build/lib/build/lib/build/lib/build/lib/clicksign/domain/signer.py
build/lib/build/lib/build/lib/build/lib/build/lib/build/lib/build/lib/clicksign/domain/interfaces/idocument.py
build/lib/build/lib/build/lib/build/lib/build/lib/build/lib/build/lib/clicksign/domain/interfaces/idocument_adapter.py
build/lib/build/lib/build/lib/build/lib/build/lib/build/lib/build/lib/clicksign/domain/interfaces/ienvelope.py
build/lib/build/lib/build/lib/build/lib/build/lib/build/lib/build/lib/clicksign/domain/interfaces/ienvelope_adapter.py
build/lib/build/lib/build/lib/build/lib/build/lib/build/lib/build/lib/clicksign/domain/interfaces/irequired_auth.py
build/lib/build/lib/build/lib/build/lib/build/lib/build/lib/build/lib/clicksign/domain/interfaces/irequired_auth_adapter.py
build/lib/build/lib/build/lib/build/lib/build/lib/build/lib/build/lib/clicksign/domain/interfaces/isigner.py
clicksign_lib_v2-0.1.8.dist-info/METADATA
clicksign_lib_v2-0.1.8.dist-info/WHEEL
clicksign_lib_v2-0.1.8.dist-info/dependency_links.txt
clicksign_lib_v2-0.1.8.dist-info/top_level.txt
clicksign_lib_v2-0.1.8.dist-info/RECORD
