Metadata-Version: 2.2
Name: clicksign_lib_v2
Version: 0.1.8
Summary: Add your description here
Author: Giorgio Frigotto Lovatel
Requires-Python: >=3.12
Requires-Dist: uuid7>=0.1.0
Dynamic: author
Dynamic: requires-python
